napari_video_cvdask/__init__.py
napari_video_cvdask/_reader.py
napari_video_cvdask/_version.py
napari_video_cvdask/napari.yaml
napari_video_cvdask/_tests/__init__.py
napari_video_cvdask/_tests/test_reader.py
napari_video_cvdask-0.2.1.dist-info/LICENSE
napari_video_cvdask-0.2.1.dist-info/METADATA
napari_video_cvdask-0.2.1.dist-info/WHEEL
napari_video_cvdask-0.2.1.dist-info/entry_points.txt
napari_video_cvdask-0.2.1.dist-info/top_level.txt
napari_video_cvdask-0.2.1.dist-info/RECORD
