Metadata-Version: 2.1
Name: napari-video-cvdask
Version: 0.2.1
Summary: A Video File Reader that uses OpenCV2 and Dask Arrays
Home-page: https://github.com/nickdelgrosso/napari-video-cvdask
Author: Nicholas A. Del Grosso
Author-email: delgrosso.nick@gmail.com
License: MIT
Project-URL: Bug Tracker, https://github.com/nickdelgrosso/napari-video-cvdask/issues
Project-URL: Documentation, https://github.com/nickdelgrosso/napari-video-cvdask#README.md
Project-URL: Source Code, https://github.com/nickdelgrosso/napari-video-cvdask
Project-URL: User Support, https://github.com/nickdelgrosso/napari-video-cvdask/issues
Platform: UNKNOWN
Classifier: Development Status :: 2 - Pre-Alpha
Classifier: Intended Audience :: Developers
Classifier: Framework :: napari
Classifier: Topic :: Software Development :: Testing
Classifier: Programming Language :: Python
Classifier: Programming Language :: Python :: 3
Classifier: Programming Language :: Python :: 3.7
Classifier: Programming Language :: Python :: 3.8
Classifier: Programming Language :: Python :: 3.9
Classifier: Programming Language :: Python :: 3.10
Classifier: Operating System :: OS Independent
Classifier: License :: OSI Approved :: MIT License
Requires-Python: >=3.7
License-File: LICENSE
Requires-Dist: dask-image
Requires-Dist: av
